pythonic_testcase.py
PythonicTestcase-1.4.1.dist-info/LICENSE.txt
PythonicTestcase-1.4.1.dist-info/METADATA
PythonicTestcase-1.4.1.dist-info/WHEEL
PythonicTestcase-1.4.1.dist-info/top_level.txt
PythonicTestcase-1.4.1.dist-info/zip-safe
PythonicTestcase-1.4.1.dist-info/RECORD
