Metadata-Version: 2.1
Name: PythonicTestcase
Version: 1.4.1
Summary: standalone pythonic assertions
Home-page: https://github.com/FelixSchwarz/pythonic-testcase
Author: Felix Schwarz
Author-email: felix.schwarz@oss.schwarz.eu
License: MIT
Project-URL: Code, https://github.com/FelixSchwarz/pythonic-testcase
Project-URL: Issue tracker, https://github.com/FelixSchwarz/pythonic-testcase/issues
Platform: UNKNOWN
Classifier: Development Status :: 5 - Production/Stable
Classifier: Intended Audience :: Developers
Classifier: License :: OSI Approved :: MIT License
Classifier: Programming Language :: Python :: 2
Classifier: Programming Language :: Python :: 3
Classifier: Topic :: Software Development :: Libraries :: Python Modules
Requires-Python: !=3.0.*,!=3.1.*,!=3.2.*,!=3.3.*,>=2.7
